nostrd/__init__.py
nostrd/nostrd.py
nostrd/package_name/__init__.py
nostrd/package_name/nostrd.py
nostrd-0.0.1b0.dist-info/LICENSE
nostrd-0.0.1b0.dist-info/METADATA
nostrd-0.0.1b0.dist-info/WHEEL
nostrd-0.0.1b0.dist-info/top_level.txt
nostrd-0.0.1b0.dist-info/RECORD
