Metadata-Version: 2.1
Name: nostrd
Version: 0.0.1b0
Summary: Nostr relay
Home-page: https://github.com/brunneis/nostrd
Author: Rodrigo Martínez Castaño
Author-email: dev@brunneis.com
License: GNU General Public License v3 (GPLv3)
Classifier: Development Status :: 4 - Beta
Classifier: Environment :: Console
Classifier: Intended Audience :: Developers
Classifier: License :: OSI Approved :: GNU General Public License v3 (GPLv3)
Classifier: Operating System :: POSIX :: Linux
Classifier: Programming Language :: Python :: 3.6
Classifier: Programming Language :: Python :: Implementation :: PyPy
Classifier: Topic :: Software Development :: Libraries :: Python Modules
Requires-Python: >=3.6
License-File: LICENSE
